{"Stages": [{"Sid": "15709", "Snm": "Group E", "Scd": "group-e", "badgeUrl": "euro-2024.png", "firstColor": "0008ff", "Cnm": "Euro 2024", "CnmT": "euro-2024", "Csnm": "Euro 2024", "Ccd": "euro-2024", "CompId": "492", "CompN": "Euro 2024", "CompD": "Europe", "Scu": 0, "Events": [{"Eid": "1085860", "Pids": {"12": "SBTE_1_30554290", "112": "SBTE_2_1020478494", "8": "1085860"}, "T1": [{"Nm": "Belgium", "ID": "9109", "Img": "enet/8263.png", "NewsTag": "/team/belgium-2021020913320920836-2206/", "Abr": "BEL"}], "T2": [{"Nm": "Romania", "ID": "9183", "Img": "enet/9730.png", "Abr": "ROU"}], "Eps": "NS", "Esid": 1, "Epr": 0, "Ecov": 0, "ErnInf": "2", "Et": 1, "Esd": 20240622190000, "EO": 496879783, "EOX": 496879783, "Spid": 1, "Pid": 8, "T1img": "https://lsm-static-prod.livescore.com/medium/enet/8263.png", "T2img": "https://lsm-static-prod.livescore.com/medium/enet/9730.png"}, {"Eid": "1085859", "Pids": {"12": "SBTE_1_30554293", "112": "SBTE_2_1020640054", "8": "1085859"}, "Tr1": "1", "Tr2": "2", "Trh1": "1", "Trh2": "0", "Tr1OR": "1", "Tr2OR": "2", "T1": [{"Nm": "Slovakia", "ID": "9011", "Img": "enet/8497.png", "NewsTag": "", "Abr": "SVK"}], "T2": [{"Nm": "Ukraine", "ID": "9245", "Img": "enet/6718.png", "NewsTag": "/team/ukraine-2021020913320920836-1858/", "Abr": "UKR"}], "Eps": "FT", "Esid": 6, "Epr": 2, "Ecov": 0, "ErnInf": "2", "Ewt": 2, "Et": 1, "Esd": 20240621130000, "EO": 371116925, "EOX": 371116925, "Spid": 1, "Pid": 8, "T1img": "https://lsm-static-prod.livescore.com/medium/enet/8497.png", "T2img": "https://lsm-static-prod.livescore.com/medium/enet/6718.png"}], "img": "https://static.livescore.com/i2/fh/euro-2024.jpg"}, {"Sid": "15710", "Snm": "Group F", "Scd": "group-f", "badgeUrl": "euro-2024.png", "firstColor": "0008ff", "Cnm": "Euro 2024", "CnmT": "euro-2024", "Csnm": "Euro 2024", "Ccd": "euro-2024", "CompId": "492", "CompN": "Euro 2024", "CompD": "Europe", "Scu": 0, "Events": [{"Eid": "1085865", "Pids": {"12": "SBTE_1_30625595", "112": "SBTE_2_1020640062", "8": "1085865"}, "T1": [{"Nm": "Georgia", "ID": "9139", "Img": "enet/8268.png", "NewsTag": "/team/georgia-2021020913320920836-1266/", "Abr": "GEO"}], "T2": [{"Nm": "Czechia", "ID": "9266", "Img": "enet/8496.png", "NewsTag": "/team/czech-republic-2022062716001253418-2348/", "Abr": "CZE"}], "Eps": "NS", "Esid": 1, "Epr": 0, "Ecov": 0, "ErnInf": "2", "Et": 1, "Esd": 20240622130000, "EO": 496552103, "EOX": 496552103, "Spid": 1, "Pid": 8, "T1img": "https://lsm-static-prod.livescore.com/medium/enet/8268.png", "T2img": "https://lsm-static-prod.livescore.com/medium/enet/8496.png"}, {"Eid": "1085866", "Pids": {"12": "SBTE_1_30554292", "112": "SBTE_2_1020478493", "8": "1085866"}, "T1": [{"Nm": "Turkiye", "ID": "9136", "Img": "enet/6595.png", "NewsTag": "/team/turkey-2021020913320920836-1845/", "Abr": "TUR"}], "T2": [{"Nm": "Portugal", "ID": "9295", "Img": "enet/8361.png", "NewsTag": "/team/portugal-2021020913320920836-1651/", "Abr": "POR"}], "Eps": "NS", "Esid": 1, "Epr": 0, "Ecov": 0, "ErnInf": "2", "Et": 1, "Esd": 20240622160000, "EO": 496879783, "EOX": 496879783, "Spid": 1, "Pid": 8, "T1img": "https://lsm-static-prod.livescore.com/medium/enet/6595.png", "T2img": "https://lsm-static-prod.livescore.com/medium/enet/8361.png"}], "img": "https://static.livescore.com/i2/fh/euro-2024.jpg"}, {"Sid": "16291", "Snm": "Group A", "Scd": "group-a", "badgeUrl": "copa-america-2024.png", "firstColor": "061d8f", "Cnm": "Copa America", "CnmT": "copa-america", "Csnm": "Copa America", "Ccd": "copa-america", "CompId": "11", "CompN": "Copa America", "CompD": "CONMEBOL", "Scu": 0, "Events": [{"Eid": "1125728", "Pids": {"12": "SBTE_1_29827299", "112": "SBTE_2_1020387287", "8": "1125728"}, "Tr1": "0", "Tr2": "0", "Trh1": "0", "Trh2": "0", "Tr1OR": "0", "Tr2OR": "0", "T1": [{"Nm": "Peru", "ID": "9031", "Img": "enet/5798.png", "Abr": "PER"}], "T2": [{"Nm": "Chile", "ID": "9032", "Img": "enet/9762.png", "Abr": "CHI"}], "Eps": "FT", "Esid": 6, "Epr": 2, "Ecov": 0, "ErnInf": "1", "Ewt": 0, "Et": 1, "Esd": 20240622000000, "EO": 337562493, "EOX": 337562493, "Spid": 1, "Pid": 8, "T1img": "https://lsm-static-prod.livescore.com/medium/enet/5798.png", "T2img": "https://lsm-static-prod.livescore.com/medium/enet/9762.png"}, {"Eid": "1154426", "Pids": {"12": "SBTE_1_30450820", "112": "SBTE_2_1020625434", "8": "1154426"}, "Tr1": "2", "Tr2": "0", "Trh1": "0", "Trh2": "0", "Tr1OR": "2", "Tr2OR": "0", "T1": [{"Nm": "Argentina", "ID": "9100", "Img": "teambadge/argentina-2024.png", "NewsTag": "/team/argentina-2021020913320920836-2153/", "Abr": "ARG"}], "T2": [{"Nm": "Canada", "ID": "335", "Img": "enet/5810.png", "NewsTag": "/team/canada-2021020913320920836-2264/", "Abr": "CAN"}], "Eps": "FT", "Esid": 6, "Epr": 2, "Ecov": 0, "ErnInf": "1", "Ewt": 1, "Et": 1, "Esd": 20240621000000, "EO": 371116925, "EOX": 371116925, "Spid": 1, "Pid": 8, "T1img": "https://lsm-static-prod.livescore.com/medium/teambadge/argentina-2024.png", "T2img": "https://lsm-static-prod.livescore.com/medium/enet/5810.png"}], "img": "https://static.livescore.com/i2/fh/copa-america.jpg"}, {"Sid": "16292", "Snm": "Group B", "Scd": "group-b", "badgeUrl": "copa-america-2024.png", "firstColor": "061d8f", "Cnm": "Copa America", "CnmT": "copa-america", "Csnm": "Copa America", "Ccd": "copa-america", "CompId": "11", "CompN": "Copa America", "CompD": "CONMEBOL", "Scu": 0, "Events": [{"Eid": "1125733", "Pids": {"12": "SBTE_1_29827301", "112": "SBTE_2_1020387286", "8": "1125733"}, "T1": [{"Nm": "Ecuador", "ID": "8973", "Img": "enet/6707.png", "NewsTag": "/team/ecuador-2021020913320920836-2377/", "Abr": "ECU"}], "T2": [{"Nm": "Venezuela", "ID": "9103", "Img": "enet/5800.png", "Abr": "VEN"}], "Eps": "NS", "Esid": 1, "Epr": 0, "Ecov": 0, "ErnInf": "1", "Et": 1, "Esd": 20240622220000, "EO": 471648423, "EOX": 471648423, "Spid": 1, "Pid": 8, "T1img": "https://lsm-static-prod.livescore.com/medium/enet/6707.png", "T2img": "https://lsm-static-prod.livescore.com/medium/enet/5800.png"}], "img": "https://static.livescore.com/i2/fh/copa-america.jpg"}, {"Sid": "16489", "Snm": "J1 League", "Scd": "j-league", "badgeUrl": "2023-japan-j1-league.png", "firstColor": "BC002D", "Cnm": "Japan", "CnmT": "japan", "Csnm": "Japan", "Ccd": "japan", "CompId": "176", "CompN": "J1 League", "CompD": "Japan", "CompST": "Japan", "Scu": 0, "Events": [{"Eid": "1157107", "Pids": {"12": "SBTE_1_30708361", "112": "SBTE_2_1020435757", "8": "1157107"}, "Tr1": "0", "Tr2": "0", "Trh1": "0", "Trh2": "0", "Tr1OR": "0", "Tr2OR": "0", "T1": [{"Nm": "Machida Zelvia", "ID": "8673", "Img": "enet/194011.png", "Abr": "MAC"}], "T2": [{"Nm": "Avispa Fukuoka", "ID": "8659", "Img": "enet/8270.png", "Abr": "AVI"}], "Eps": "FT", "Esid": 6, "Epr": 2, "Ecov": 0, "ErnInf": "19", "Ewt": 0, "Et": 1, "Esd": 20240622060000, "EO": 807289725, "EOX": 807289725, "Spid": 1, "Pid": 8, "T1img": "https://lsm-static-prod.livescore.com/medium/enet/194011.png", "T2img": "https://lsm-static-prod.livescore.com/medium/enet/8270.png"}, {"Eid": "1157125", "Pids": {"12": "SBTE_1_30708768", "112": "SBTE_2_1020435740", "8": "1157125"}, "Tr1": "2", "Tr2": "1", "Trh1": "0", "Trh2": "1", "Tr1OR": "2", "Tr2OR": "1", "T1": [{"Nm": "Albirex Niigata", "ID": "8685", "Img": "enet/4425.png", "Abr": "ALB"}], "T2": [{"Nm": "Kawasaki Frontale", "ID": "7608", "Img": "enet/6304.png", "Abr": "KAW"}], "Eps": "FT", "Esid": 3, "Epr": 1, "Ecov": 0, "ErnInf": "19", "Et": 1, "Esd": 20240622090000, "EO": 807322495, "EOX": 807322495, "Spid": 1, "Pid": 8, "T1img": "https://lsm-static-prod.livescore.com/medium/enet/4425.png", "T2img": "https://lsm-static-prod.livescore.com/medium/enet/6304.png"}, {"Eid": "1157121", "Pids": {"12": "SBTE_1_30708767", "112": "SBTE_2_1020435759", "8": "1157121"}, "Tr1": "1", "Tr2": "0", "Trh1": "0", "Trh2": "0", "Tr1OR": "1", "Tr2OR": "0", "T1": [{"Nm": "Tokyo Verdy", "ID": "8638", "Img": "enet/6223.png", "Abr": "TOK"}], "T2": [{"Nm": "Nagoya Grampus Eight", "ID": "7529", "Img": "enet/8006.png", "Abr": "NAG"}], "Eps": "FT", "Esid": 6, "Epr": 2, "Ecov": 0, "ErnInf": "19", "Ewt": 1, "Et": 1, "Esd": 20240622090000, "EO": 807289725, "EOX": 807289725, "Spid": 1, "Pid": 8, "T1img": "https://lsm-static-prod.livescore.com/medium/enet/6223.png", "T2img": "https://lsm-static-prod.livescore.com/medium/enet/8006.png"}, {"Eid": "1157175", "Pids": {"12": "SBTE_1_30708769", "112": "SBTE_2_1020435746", "8": "1157175"}, "Tr1": "2", "Tr2": "1", "Trh1": "0", "Trh2": "0", "Tr1OR": "2", "Tr2OR": "1", "T1": [{"Nm": "Gamba Osaka", "ID": "7602", "Img": "enet/6582.png", "Abr": "GAM"}], "T2": [{"Nm": "Vissel Kobe", "ID": "4841", "Img": "enet/4688.png", "Abr": "VIS"}], "Eps": "FT", "Esid": 3, "Epr": 1, "Ecov": 0, "ErnInf": "19", "Et": 1, "Esd": 20240622093000, "EO": 807322495, "EOX": 807322495, "Spid": 1, "Pid": 8, "T1img": "https://lsm-static-prod.livescore.com/medium/enet/6582.png", "T2img": "https://lsm-static-prod.livescore.com/medium/enet/4688.png"}, {"Eid": "1157173", "Pids": {"12": "SBTE_1_30708770", "112": "SBTE_2_1020435741", "8": "1157173"}, "Tr1": "1", "Tr2": "1", "Trh1": "0", "Trh2": "0", "Tr1OR": "1", "Tr2OR": "1", "T1": [{"Nm": "Jubilo Iwata", "ID": "7554", "Img": "enet/8065.png", "Abr": "JUB"}], "T2": [{"Nm": "Cerezo Osaka", "ID": "7548", "Img": "enet/4692.png", "Abr": "CER"}], "Eps": "FT", "Esid": 3, "Epr": 1, "Ecov": 0, "ErnInf": "19", "Et": 1, "Esd": 20240622093000, "EO": 807289727, "EOX": 807289727, "Spid": 1, "Pid": 8, "T1img": "https://lsm-static-prod.livescore.com/medium/enet/8065.png", "T2img": "https://lsm-static-prod.livescore.com/medium/enet/4692.png"}, {"Eid": "1157176", "Pids": {"12": "SBTE_1_30711721", "112": "SBTE_2_1020435743", "8": "1157176"}, "Tr1": "0", "Tr2": "1", "Trh1": "0", "Trh2": "1", "Tr1OR": "0", "Tr2OR": "1", "T1": [{"Nm": "Kashiwa Reysol", "ID": "8669", "Img": "enet/8699.png", "Abr": "KAS"}], "T2": [{"Nm": "Sanfrecce Hiroshima", "ID": "7564", "Img": "enet/6224.png", "Abr": "SAN"}], "Eps": "FT", "Esid": 10, "Epr": 1, "Ecov": 0, "ErnInf": "19", "Et": 1, "Esd": 20240622100000, "EO": 807289711, "EOX": 807289711, "Spid": 1, "Pid": 8, "T1img": "https://lsm-static-prod.livescore.com/medium/enet/8699.png", "T2img": "https://lsm-static-prod.livescore.com/medium/enet/6224.png"}, {"Eid": "1157192", "Pids": {"12": "SBTE_1_30708360", "112": "SBTE_2_1020435776", "8": "1157192"}, "Tr1": "3", "Tr2": "0", "Trh1": "0", "Trh2": "0", "Tr1OR": "3", "Tr2OR": "0", "T1": [{"Nm": "Sagan Tosu", "ID": "7609", "Img": "enet/162193.png", "Abr": "SAG"}], "T2": [{"Nm": "Kyoto Sanga FC", "ID": "8670", "Img": "enet/8542.png", "Abr": "KYO"}], "Eps": "FT", "Esid": 10, "Epr": 1, "Ecov": 0, "ErnInf": "19", "Et": 1, "Esd": 20240622100000, "EO": 807158639, "EOX": 807158639, "Spid": 1, "Pid": 8, "T1img": "https://lsm-static-prod.livescore.com/medium/enet/162193.png", "T2img": "https://lsm-static-prod.livescore.com/medium/enet/8542.png"}, {"Eid": "1157188", "Pids": {"12": "SBTE_1_30708775", "112": "SBTE_2_1020435773", "8": "1157188"}, "Tr1": "0", "Tr2": "1", "Trh1": "0", "Trh2": "0", "Tr1OR": "0", "Tr2OR": "1", "T1": [{"Nm": "Shonan Bellmare", "ID": "6759", "Img": "enet/6180.png", "Abr": "SHO"}], "T2": [{"Nm": "FC Tokyo", "ID": "7606", "Img": "enet/4399.png", "Abr": "FCT"}], "Eps": "FT", "Esid": 10, "Epr": 1, "Ecov": 0, "ErnInf": "19", "Et": 1, "Esd": 20240622100000, "EO": 807158639, "EOX": 807158639, "Spid": 1, "Pid": 8, "T1img": "https://lsm-static-prod.livescore.com/medium/enet/6180.png", "T2img": "https://lsm-static-prod.livescore.com/medium/enet/4399.png"}, {"Eid": "1157185", "Pids": {"12": "SBTE_1_30708774", "112": "SBTE_2_1020435748", "8": "1157185"}, "Tr1": "2", "Tr2": "2", "Trh1": "0", "Trh2": "2", "Tr1OR": "2", "Tr2OR": "2", "T1": [{"Nm": "Urawa Red Diamonds", "ID": "7601", "Img": "enet/6244.png", "Abr": "URA"}], "T2": [{"Nm": "Kashima Antlers", "ID": "4842", "Img": "enet/4397.png", "Abr": "KAS"}], "Eps": "FT", "Esid": 10, "Epr": 1, "Ecov": 0, "ErnInf": "19", "Et": 1, "Esd": 20240622100000, "EO": 807322479, "EOX": 807322479, "Spid": 1, "Pid": 8, "T1img": "https://lsm-static-prod.livescore.com/medium/enet/6244.png", "T2img": "https://lsm-static-prod.livescore.com/medium/enet/4397.png"}], "img": "https://static.livescore.com/i2/fh/japan.jpg"}, {"Sid": "16665", "Snm": "K-League 1", "Scd": "k-league-1", "badgeUrl": "2023-korea-k-league-1.png", "firstColor": "021858", "Cnm": "Republic of Korea", "CnmT": "republic-of-korea", "Csnm": "Republic of Korea", "Ccd": "korea-republic", "CompId": "195", "CompN": "K League 1", "CompD": "Republic of Korea", "Scu": 0, "Events": [{"Eid": "1151219", "Pids": {"12": "SBTE_1_30708967", "112": "SBTE_2_1020415939", "8": "1151219"}, "Tr1": "3", "Tr2": "0", "Trh1": "1", "Trh2": "0", "Tr1OR": "3", "Tr2OR": "0", "T1": [{"Nm": "Daegu FC", "ID": "8143", "Img": "enet/133897.png", "Abr": "DAE"}], "T2": [{"Nm": "Jeonbuk FC", "ID": "7194", "Img": "enet/46038.png", "Abr": "JEO"}], "Eps": "FT", "Esid": 3, "Epr": 1, "Ecov": 0, "ErnInf": "18", "Et": 1, "Esd": 20240622090000, "EO": 807289727, "EOX": 807289727, "Spid": 1, "Pid": 8, "T1img": "https://lsm-static-prod.livescore.com/medium/enet/133897.png", "T2img": "https://lsm-static-prod.livescore.com/medium/enet/46038.png"}, {"Eid": "1151226", "Pids": {"12": "SBTE_1_30705627", "112": "SBTE_2_1020415954", "8": "1151226"}, "Tr1": "2", "Tr2": "1", "Trh1": "0", "Trh2": "1", "Tr1OR": "2", "Tr2OR": "1", "T1": [{"Nm": "Daejeon Citizen", "ID": "9803", "Img": "enet/133900.png", "Abr": "DAE"}], "T2": [{"Nm": "Gwangju FC", "ID": "9804", "Img": "enet/245905.png", "Abr": "GWA"}], "Eps": "FT", "Esid": 10, "Epr": 1, "Ecov": 0, "ErnInf": "18", "Et": 1, "Esd": 20240622100000, "EO": 807289727, "EOX": 807289727, "Spid": 1, "Pid": 8, "T1img": "https://lsm-static-prod.livescore.com/medium/enet/133900.png", "T2img": "https://lsm-static-prod.livescore.com/medium/enet/245905.png"}, {"Eid": "1151229", "Pids": {"12": "SBTE_1_30705668", "112": "SBTE_2_1020415962", "8": "1151229"}, "Tr1": "2", "Tr2": "3", "Trh1": "2", "Trh2": "3", "Tr1OR": "2", "Tr2OR": "3", "T1": [{"Nm": "Gangwon FC", "ID": "8099", "Img": "enet/164734.png", "Abr": "GAN"}], "T2": [{"Nm": "Gimcheon Sangmu", "ID": "8260", "Img": "enet/133901.png", "Abr": "SAN"}], "Eps": "FT", "Esid": 10, "Epr": 1, "Ecov": 0, "ErnInf": "18", "Et": 1, "Esd": 20240622100000, "EO": 807289711, "EOX": 807289711, "Spid": 1, "Pid": 8, "T1img": "https://lsm-static-prod.livescore.com/medium/enet/164734.png", "T2img": "https://lsm-static-prod.livescore.com/medium/enet/133901.png"}, {"Eid": "1151233", "Pids": {"12": "SBTE_1_30708776", "112": "SBTE_2_1020415960", "8": "1151233"}, "T1": [{"Nm": "FC Seoul", "ID": "303", "Img": "enet/92630.png", "Abr": "FCS"}], "T2": [{"Nm": "Suwon FC", "ID": "9792", "Img": "enet/187951.png", "Abr": "SUW"}], "Eps": "59'", "Esid": 1, "Epr": 0, "Ecov": 0, "ErnInf": "18", "Et": 1, "Esd": 20240622110000, "EO": 815546471, "EOX": 815546471, "Spid": 1, "Pid": 8, "T1img": "https://lsm-static-prod.livescore.com/medium/enet/92630.png", "T2img": "https://lsm-static-prod.livescore.com/medium/enet/187951.png", "Tr1": "1", "Tr2": "0", "Tr1OR": "1", "Tr2OR": "0", "Trh1": "1", "Trh2": "0"}], "img": "https://static.livescore.com/i2/fh/korea-republic.jpg"}, {"Sid": "15708", "Snm": "Group D", "Scd": "group-d", "badgeUrl": "euro-2024.png", "firstColor": "0008ff", "Cnm": "Euro 2024", "CnmT": "euro-2024", "Csnm": "Euro 2024", "Ccd": "euro-2024", "CompId": "492", "CompN": "Euro 2024", "CompD": "Europe", "Scu": 0, "Events": [{"Eid": "1085854", "Pids": {"12": "SBTE_1_30554294", "112": "SBTE_2_1020640058", "8": "1085854"}, "Tr1": "1", "Tr2": "3", "Trh1": "1", "Trh2": "1", "Tr1OR": "1", "Tr2OR": "3", "T1": [{"Nm": "Poland", "ID": "8993", "Img": "teambadge/poland-2024.png", "NewsTag": "/team/poland-2021020913320920836-1645/", "Abr": "POL"}], "T2": [{"Nm": "Austria", "ID": "9161", "Img": "enet/8255.png", "NewsTag": "/team/austria-2021020913320920836-2185/", "Abr": "AUT"}], "Eps": "FT", "Esid": 6, "Epr": 2, "Ecov": 0, "ErnInf": "2", "Ewt": 2, "Et": 1, "Esd": 20240621160000, "EO": 371116925, "EOX": 371116925, "Spid": 1, "Pid": 8, "T1img": "https://lsm-static-prod.livescore.com/medium/teambadge/poland-2024.png", "T2img": "https://lsm-static-prod.livescore.com/medium/enet/8255.png"}, {"Eid": "1085853", "Pids": {"12": "SBTE_1_30554291", "112": "SBTE_2_1020478504", "8": "1085853"}, "Tr1": "0", "Tr2": "0", "Trh1": "0", "Trh2": "0", "Tr1OR": "0", "Tr2OR": "0", "T1": [{"Nm": "Netherlands", "ID": "8967", "Img": "enet/6708.png", "NewsTag": "/team/netherlands-2022062716001253418-1562/", "Abr": "NLD"}], "T2": [{"Nm": "France", "ID": "9179", "Img": "enet/6723.png", "NewsTag": "/team/france-2021020913320920836-2434/", "Abr": "FRA"}], "Eps": "FT", "Esid": 6, "Epr": 2, "Ecov": 0, "ErnInf": "2", "Ewt": 0, "Et": 1, "Esd": 20240621190000, "EO": 371116925, "EOX": 371116925, "Spid": 1, "Pid": 8, "T1img": "https://lsm-static-prod.livescore.com/medium/enet/6708.png", "T2img": "https://lsm-static-prod.livescore.com/medium/enet/6723.png"}], "img": "https://static.livescore.com/i2/fh/euro-2024.jpg"}]}