{"Eid": "1155035", "Pids": {"8": "1155035", "1": "4408797", "12": "SBTE_1_30703531", "112": "SBTE_2_1020999697", "6": "46927361", "32": "2886321"}, "Sids": {"8": "16571", "1": "890157", "12": "SBTC3_33422", "112": "SBTC3_212502", "6": "81143", "32": "21526"}, "Tr1": "1", "Tr2": "1", "Trh1": "1", "Trh2": "1", "Tr1OR": "1", "Tr2OR": "1", "T1": [{"Nm": "Villa Dalmine", "ID": "6880", "Img": "enet/298630.png", "Abr": "VIL", "tbd": 0, "Gd": 1, "Pids": {"12": ["SBTP_1_117638"], "1": ["298630"], "112": ["SBTP_2_1001505827"], "6": ["112509"], "8": ["6880"], "32": ["2172"]}, "CoNm": "Argentina", "CoId": "ARG", "HasVideo": false, "TO": 2}], "T2": [{"Nm": "CSD Flandria", "ID": "5149", "Img": "enet/213537.png", "Abr": "FLA", "tbd": 0, "Gd": 1, "Pids": {"12": ["SBTP_1_112026"], "1": ["213537"], "112": ["SBTP_2_1000721409"], "6": ["112505"], "8": ["5149"], "32": ["3807"]}, "CoNm": "Argentina", "CoId": "ARG", "HasVideo": false, "TO": 2}], "Eps": "FT", "Esid": 6, "Epr": 2, "Ecov": 0, "Ern": 21, "ErnInf": "21", "Ewt": 0, "Et": 1, "Esd": 20240615180000, "Edf": 20240615195421, "Eact": 1, "EO": 807141389, "EOX": 807141389, "LuC": 0, "Ehid": 0, "Spid": 1, "Stg": {"Sid": "16571", "Snm": "Primera B Metropolitana: Apertura", "Scd": "primera-b-metropolitana-apertura", "Cid": "75", "Cnm": "Argentina", "CnmT": "argentina", "Csnm": "Argentina", "Ccd": "argentina", "Scu": 0, "Sds": "Primera B Metropolitana: Apertura", "Chi": 0, "Shi": 0, "Ccdiso": "ARG", "Sdn": "Primera B Metropolitana: Apertura"}, "Pid": 8, "Eloff": 0, "Incs-s": {"1": [{"Min": 12, "Nm": 2, "ID": "1458186", "Pnum": 0, "Pn": "Cristian Cuenca", "PnumO": 0, "IT": 36, "Sc": [0, 1], "Sor": 1}, {"Min": 20, "Nm": 1, "ID": "1339586", "Pnum": 0, "Pn": "Hector Javier Arias", "PnumO": 0, "IT": 36, "Sc": [1, 1], "Sor": 2}]}, "T1img": "https://lsm-static-prod.livescore.com/medium/enet/298630.png", "T2img": "https://lsm-static-prod.livescore.com/medium/enet/213537.png", "livetv": {"liveurl": [], "radarurl": ""}}