{"Eid": "1195281", "Pids": {"1": "4447675", "12": "SBTE_1_30744757", "112": "SBTE_2_1021037688", "36": "1zwgaxe3y8b79rdxnezkv13bo", "6": "48740229", "8": "1195281", "32": "2899720"}, "Sids": {"1": "891451", "12": "SBTC3_42100", "112": "SBTC3_42100", "36": "9nbpdi9q3ywcm4q0j5u0ekwcq", "6": "82489", "8": "17203", "32": "22173"}, "T1": [{"Nm": "Iguatu", "ID": "12591", "Img": "enet/584281.png", "Abr": "IGU", "tbd": 0, "Gd": 1, "Pids": {"12": ["SBTP_1_465065"], "1": ["584281"], "112": ["SBTP_2_1004185250"], "36": ["e6r10i3zrousv07o04aktjgf0"], "6": ["401927"], "8": ["12591"], "32": ["19746"]}, "CoNm": "Brazil", "CoId": "BRA", "HasVideo": false, "TO": 2}], "T2": [{"Nm": "Maracana EC", "ID": "201189", "Img": "enet/410825.png", "Abr": "MAR", "tbd": 0, "Gd": 1, "Pids": {"12": ["SBTP_1_329189"], "1": ["410825"], "112": ["SBTP_2_1001468696"], "36": ["azjv8kezptezsjhtg41uc3fds"], "6": ["87156"], "8": ["201189"], "32": ["12605"]}, "CoNm": "Brazil", "CoId": "BRA", "HasVideo": false, "TO": 0}], "Eps": "NS", "Esid": 1, "Epr": 0, "Ecov": 2, "Ern": 10, "ErnInf": "10", "Et": 1, "Esd": 20240627220000, "Eact": 1, "EO": 807145478, "EOX": 807145478, "LuC": 0, "Ehid": 0, "Spid": 1, "Stg": {"Sid": "17203", "Snm": "Serie D: Group A3", "Scd": "serie-d-group-a-3", "Cid": "172", "Cnm": "Brazil", "CnmT": "brazil", "Csnm": "Brazil", "Ccd": "brazil", "CompId": "245", "CompN": "Serie D", "CompD": "Brazil", "Scu": 0, "Sds": "Serie D: Group A3", "Chi": 0, "Shi": 0, "Ccdiso": "BRA", "Sdn": "Serie D: Group A3"}, "Pid": 8, "Eloff": 0, "T1img": "https://lsm-static-prod.livescore.com/medium/enet/584281.png", "T2img": "https://lsm-static-prod.livescore.com/medium/enet/410825.png", "livetv": {"liveurl": [], "radarurl": "https://10374b4c9e4.vws.vegacdn.vn/football/animate?profile=QYKKHVHxBfXH3&id=dn1m1gh2p963moe&lang=en"}}