{"Eid": "1226933", "Pids": {"112": "SBTE_2_1021001423", "6": "48222383", "8": "1226933"}, "Sids": {"112": "SBTC3_92659", "6": "82119", "8": "17020"}, "Tr1": "2", "Tr2": "2", "Tr1OR": "2", "Tr2OR": "2", "T1": [{"Nm": "Racing Club Women", "ID": "209065", "NewsTag": "", "Abr": "RAC", "tbd": 0, "Gd": 2, "Pids": {"112": ["SBTP_2_1004996054"], "6": ["502898"], "8": ["209065"]}, "CoNm": "Argentina", "CoId": "ARG", "HasVideo": false, "TO": 0}], "T2": [{"Nm": "Belgrano de Cordoba Women", "ID": "247288", "NewsTag": "", "Abr": "BEL", "tbd": 0, "Gd": 2, "Pids": {"112": ["SBTP_2_1028364553"], "6": ["676705"], "8": ["247288"]}, "CoNm": "Argentina", "CoId": "ARG", "HasVideo": false, "TO": 0}], "Eps": "FT", "Esid": 6, "Epr": 2, "Ecov": 2, "Ewt": 0, "Et": 1, "Esd": 20240614180000, "Edf": 20240614195951, "Eds": 20240614180000, "Eact": 1, "EO": 807145476, "EOX": 807145476, "LuC": 0, "Ehid": 0, "Spid": 1, "Stg": {"Sid": "17020", "Snm": "Women's Primera Division A", "Scd": "womens-primera-division-a", "Cid": "75", "Cnm": "Argentina", "CnmT": "argentina", "Csnm": "Argentina", "Ccd": "argentina", "Scu": 0, "Sds": "Women's Primera Division A", "Chi": 0, "Shi": 0, "Ccdiso": "ARG", "Sdn": "Women's Primera Division A"}, "Pid": 8}