{"Eid": "1250126", "Pids": {"8": "1250126", "12": "SBTE_1_30718604", "6": "50820401"}, "Sids": {"8": "16650", "12": "SBTC3_12618", "112": "SBTC3_12618", "6": "855-2024"}, "T1": [{"Nm": "Paraguay U20", "ID": "12596", "Img": "enet/5877.png", "Abr": "PAR", "tbd": 0, "Gd": 1, "Pids": {"12": ["SBTP_1_24006"], "1": ["5877"], "112": ["SBTP_2_1000013556"], "6": ["22706"], "8": ["12596"]}, "CoNm": "Paraguay", "CoId": "PRY", "HasVideo": false, "TO": 0}], "T2": [{"Nm": "Ecuador U20", "ID": "11716", "Img": "enet/263041.png", "Abr": "ECU", "tbd": 0, "Gd": 1, "Pids": {"12": ["SBTP_1_24066"], "1": ["263041"], "112": ["SBTP_2_1000013316"], "6": ["33758"], "8": ["11716"], "32": ["18811"]}, "CoNm": "Ecuador", "CoId": "ECU", "HasVideo": false, "TO": 2}], "Eps": "NS", "Esid": 1, "Epr": 0, "Ecov": 2, "Ewt": 0, "Et": 1, "Esd": 20240619204500, "Eds": 20240619204500, "Eact": 1, "EO": 269766662, "EOX": 269766662, "LuC": 0, "Ehid": 0, "Spid": 1, "Stg": {"Sid": "16650", "Snm": "Friendlies U20", "Scd": "friendlies-under-20", "Cid": "576", "Cnm": "International Friendlies", "CnmT": "international-friendlies", "Ccd": "international-friendlies", "Scu": 1, "Chi": 0, "Shi": 0, "Ccdiso": "NON", "Sdn": "Friendlies U20"}, "Pid": 8, "T1img": "https://lsm-static-prod.livescore.com/medium/enet/5877.png", "T2img": "https://lsm-static-prod.livescore.com/medium/enet/263041.png", "livetv": {"liveurl": [], "radarurl": ""}}