{"Eid": "1250406", "Pids": {"12": "SBTE_1_30723990", "6": "50823091", "8": "1250406"}, "Sids": {"12": "SBTC3_12618", "112": "SBTC3_12618", "6": "855-2024", "8": "16650"}, "T1": [{"Nm": "Ecuador U20", "ID": "11716", "Img": "enet/263041.png", "NewsTag": "", "Abr": "ECU", "tbd": 0, "Gd": 1, "Pids": {"12": ["SBTP_1_24066"], "1": ["263041"], "112": ["SBTP_2_1000013316"], "6": ["33758"], "8": ["11716"], "32": ["18811"]}, "CoNm": "Ecuador", "CoId": "ECU", "HasVideo": false, "TO": 2}], "T2": [{"Nm": "Canada U20", "ID": "14602", "Img": "enet/5869.png", "NewsTag": "", "Abr": "CAN", "tbd": 0, "Gd": 1, "Pids": {"12": ["SBTP_1_30044"], "1": ["5869"], "112": ["SBTP_2_1000026501"], "6": ["7546"], "8": ["14602"], "32": ["15138"]}, "CoNm": "Canada", "CoId": "CAN", "HasVideo": false, "TO": 2}], "Eps": "NS", "Esid": 1, "Epr": 0, "Ecov": 2, "Ewt": 0, "Et": 1, "Esd": 20240621224500, "Eds": 20240621224500, "Eact": 1, "EO": 269504518, "EOX": 269504518, "LuC": 0, "Ehid": 0, "Spid": 1, "Stg": {"Sid": "16650", "Snm": "Friendlies U20", "Scd": "friendlies-under-20", "Cid": "576", "Cnm": "International Friendlies", "CnmT": "international-friendlies", "Ccd": "international-friendlies", "Scu": 1, "Chi": 0, "Shi": 0, "Ccdiso": "NON", "Sdn": "Friendlies U20"}, "Pid": 8, "T1img": "https://lsm-static-prod.livescore.com/medium/enet/263041.png", "T2img": "https://lsm-static-prod.livescore.com/medium/enet/5869.png", "livetv": {"liveurl": [], "radarurl": ""}}