{"Eid": "1254495", "Pids": {"36": "1ytltaeiz80syksomwyh3p3pw", "6": "50649271", "8": "1254495"}, "Sids": {"1": "889181", "12": "SBTC3_92191", "112": "SBTC3_92191", "36": "4nidzmunvpvxk1ir9b6m8mpay", "6": "853-2024", "8": "16386", "32": "21332"}, "T1": [{"Nm": "Botev Plovdiv", "ID": "6558", "Img": "enet/10131.png", "Abr": "BOT", "tbd": 0, "Gd": 1, "Pids": {"12": ["SBTP_1_5930"], "1": ["10131"], "112": ["SBTP_2_1000451770"], "36": ["4410w9r2fza5ruwgcv0b2kz3"], "6": ["5241"], "8": ["6558"], "30": ["fa4deeb5-a05e-4ff9-886d-693a44978ab3"], "32": ["11"]}, "CoNm": "Bulgaria", "CoId": "BGR", "HasVideo": false, "TO": 2}], "T2": [{"Nm": "Beroe", "ID": "6745", "Img": "enet/10126.png", "Abr": "BER", "tbd": 0, "Gd": 1, "Pids": {"12": ["SBTP_1_3579"], "1": ["10126"], "112": ["SBTP_2_1000593286"], "36": ["a4wlpee3xss8dpq53asz12plz"], "6": ["3281"], "8": ["6745"], "30": ["4cc4a062-dd4a-474a-a2f8-1efbc96471c3"], "32": ["4"]}, "CoNm": "Bulgaria", "CoId": "BGR", "HasVideo": false, "TO": 2}], "Eps": "NS", "Esid": 1, "Epr": 0, "Ecov": 2, "Ewt": 0, "Et": 1, "Esd": 20240622120000, "Eds": 20240622120000, "Eact": 1, "EO": 269774854, "EOX": 269774854, "LuC": 0, "Ehid": 0, "Spid": 1, "Stg": {"Sid": "16386", "Snm": "Club Friendlies 2024", "Scd": "club-friendlies-2024", "Cid": "555", "Cnm": "Club Friendlies", "CnmT": "club-friendlies", "Csnm": "Club Friendlies", "Ccd": "club-friendlies", "CompId": "310", "CompN": "Club Friendlies", "CompD": "2024", "Scu": 1, "Sds": "Club Friendlies 2024", "Chi": 0, "Shi": 0, "Ccdiso": "NON", "Sdn": "Club Friendlies 2024"}, "Pid": 8, "T1img": "https://lsm-static-prod.livescore.com/medium/enet/10131.png", "T2img": "https://lsm-static-prod.livescore.com/medium/enet/10126.png", "livetv": {"liveurl": [], "radarurl": ""}}