{"Eid": "1254510", "Pids": {"36": "4ywuyxwv61en7bijbzkwf87bo", "6": "50849107", "8": "1254510"}, "Sids": {"1": "889181", "12": "SBTC3_92191", "112": "SBTC3_92191", "36": "4nidzmunvpvxk1ir9b6m8mpay", "6": "853-2024", "8": "16386", "32": "21332"}, "Tr1": "2", "Tr2": "3", "Trh1": "2", "Trh2": "2", "Tr1OR": "2", "Tr2OR": "3", "T1": [{"Nm": "Alianza Lima", "ID": "6403", "Img": "enet/6398.png", "Abr": "ALI", "tbd": 0, "Gd": 1, "Pids": {"12": ["SBTP_1_2751"], "1": ["6398"], "112": ["SBTP_2_1000061976"], "36": ["dv7t1octbjjnwsp3vlns10n8c"], "15": ["1611"], "6": ["2311"], "8": ["6403"], "30": ["85529c94-93d4-4702-8494-4cda664dbd89"], "32": ["1625"]}, "CoNm": "Peru", "CoId": "PER", "HasVideo": false, "TO": 2}], "T2": [{"Nm": "Bolivar", "ID": "4930", "Img": "enet/5983.png", "Abr": "BLV", "tbd": 0, "Gd": 1, "Pids": {"1": ["5983"], "112": ["SBTP_2_1000026246"], "36": ["dj7mlv2txjphj4xtannqj8q6z"], "15": ["1572"], "6": ["7059"], "8": ["4930"], "30": ["929f7fc5-97e8-4944-8872-f8aeaef2e0f1"], "32": ["2222"]}, "CoNm": "Bolivia", "CoId": "BOL", "HasVideo": false, "TO": 2}], "Eps": "FT", "Esid": 6, "Epr": 2, "Ecov": 0, "Ewt": 2, "Et": 1, "Esd": 20240627010000, "Edf": 20240627031412, "Eds": 20240627010000, "Eact": 1, "EO": 269500421, "EOX": 269500421, "LuC": 0, "Ehid": 0, "Spid": 1, "Stg": {"Sid": "16386", "Snm": "Club Friendlies 2024", "Scd": "club-friendlies-2024", "Cid": "555", "Cnm": "Club Friendlies", "CnmT": "club-friendlies", "Csnm": "Club Friendlies", "Ccd": "club-friendlies", "CompId": "310", "CompN": "Club Friendlies", "CompD": "2024", "Scu": 1, "Sds": "Club Friendlies 2024", "Chi": 0, "Shi": 0, "Ccdiso": "NON", "Sdn": "Club Friendlies 2024"}, "Pid": 8, "T1img": "https://lsm-static-prod.livescore.com/medium/enet/6398.png", "T2img": "https://lsm-static-prod.livescore.com/medium/enet/5983.png", "livetv": {"liveurl": [], "radarurl": ""}}